queue8/__init__.py
queue8/listener.py
tests/__init__.py
queue8-0.1.3.dist-info/LICENSE
queue8-0.1.3.dist-info/METADATA
queue8-0.1.3.dist-info/WHEEL
queue8-0.1.3.dist-info/top_level.txt
queue8-0.1.3.dist-info/RECORD
